kcprov/__init__.py
kcprov/main.py
kcprov-0.2.3.dist-info/METADATA
kcprov-0.2.3.dist-info/WHEEL
kcprov-0.2.3.dist-info/entry_points.txt
kcprov-0.2.3.dist-info/RECORD
