Metadata-Version: 2.4
Name: kcprov
Version: 0.2.3
Summary: Utilities for provisioning Keycloak
Author-email: Griddot <info@griddot.net>
Classifier: Intended Audience :: Developers
Classifier: Natural Language :: English
Requires-Python: >=3.12
Requires-Dist: click
